COCO_LICENSE
LICENSE
MANIFEST.in
README.md
pyproject.toml
requirements-dev.txt
requirements.txt
setup.py
data/example_1.csv
data/example_2.csv
src/aac_metrics/__init__.py
src/aac_metrics/__main__.py
src/aac_metrics/download.py
src/aac_metrics/eval.py
src/aac_metrics/info.py
src/aac_metrics.egg-info/PKG-INFO
src/aac_metrics.egg-info/SOURCES.txt
src/aac_metrics.egg-info/dependency_links.txt
src/aac_metrics.egg-info/entry_points.txt
src/aac_metrics.egg-info/requires.txt
src/aac_metrics.egg-info/top_level.txt
src/aac_metrics/classes/__init__.py
src/aac_metrics/classes/base.py
src/aac_metrics/classes/bert_score_mrefs.py
src/aac_metrics/classes/bleu.py
src/aac_metrics/classes/cider_d.py
src/aac_metrics/classes/clap_sim.py
src/aac_metrics/classes/evaluate.py
src/aac_metrics/classes/fense.py
src/aac_metrics/classes/fer.py
src/aac_metrics/classes/mace.py
src/aac_metrics/classes/meteor.py
src/aac_metrics/classes/rouge_l.py
src/aac_metrics/classes/sbert_sim.py
src/aac_metrics/classes/spice.py
src/aac_metrics/classes/spider.py
src/aac_metrics/classes/spider_fl.py
src/aac_metrics/classes/spider_max.py
src/aac_metrics/classes/vocab.py
src/aac_metrics/functional/__init__.py
src/aac_metrics/functional/bert_score_mrefs.py
src/aac_metrics/functional/bleu.py
src/aac_metrics/functional/cider_d.py
src/aac_metrics/functional/clap_sim.py
src/aac_metrics/functional/evaluate.py
src/aac_metrics/functional/fense.py
src/aac_metrics/functional/fer.py
src/aac_metrics/functional/mace.py
src/aac_metrics/functional/meteor.py
src/aac_metrics/functional/mult_cands.py
src/aac_metrics/functional/rouge_l.py
src/aac_metrics/functional/sbert_sim.py
src/aac_metrics/functional/spice.py
src/aac_metrics/functional/spider.py
src/aac_metrics/functional/spider_fl.py
src/aac_metrics/functional/spider_max.py
src/aac_metrics/functional/vocab.py
src/aac_metrics/utils/__init__.py
src/aac_metrics/utils/checks.py
src/aac_metrics/utils/collections.py
src/aac_metrics/utils/globals.py
src/aac_metrics/utils/tokenization.py
tests/test_compatibility_caption_evaluation_tools.py
tests/test_compatibility_fense.py
tests/test_compatibility_mace.py
tests/test_compatibility_torchmetrics.py
tests/test_doc_examples.py
tests/test_pickable.py
tests/test_pipeline.py
