Metadata-Version: 2.4
Name: aac-metrics
Version: 0.6.0
Summary: Metrics for evaluating Automated Audio Captioning systems, designed for PyTorch.
Author-email: "Étienne Labbé (Labbeti)" <labbeti.pub@gmail.com>
Maintainer-email: "Étienne Labbé (Labbeti)" <labbeti.pub@gmail.com>
Project-URL: Homepage, https://pypi.org/project/aac-metrics/
Project-URL: Documentation, https://aac-metrics.readthedocs.io/
Project-URL: Repository, https://github.com/Labbeti/aac-metrics.git
Project-URL: Changelog, https://github.com/Labbeti/aac-metrics/blob/main/CHANGELOG.md
Project-URL: Tracker, https://github.com/Labbeti/aac-metrics/issues
Keywords: audio,metrics,text,captioning,audio-captioning
Classifier: Intended Audience :: Science/Research
Classifier: Programming Language :: Python :: 3
Classifier: Programming Language :: Python :: 3.9
Classifier: Programming Language :: Python :: 3.10
Classifier: Programming Language :: Python :: 3.11
Classifier: Programming Language :: Python :: 3.12
Classifier: Programming Language :: Python :: 3.13
Classifier: Topic :: Scientific/Engineering
Classifier: Topic :: Scientific/Engineering :: Artificial Intelligence
Classifier: Operating System :: POSIX :: Linux
Classifier: Operating System :: MacOS
Requires-Python: >=3.9
License-File: LICENSE
License-File: COCO_LICENSE
Requires-Dist: msclap~=1.3.3
Requires-Dist: numpy>=1.21.2
Requires-Dist: pythonwrench<0.4.0,>=0.3.0
Requires-Dist: pyyaml>=6.0
Requires-Dist: sentence-transformers>=2.2.2
Requires-Dist: torch>=1.10.1
Requires-Dist: torchmetrics>=0.11.4
Requires-Dist: tqdm>=4.64.0
Requires-Dist: transformers
Provides-Extra: dev
Requires-Dist: black==23.12.1; extra == "dev"
Requires-Dist: coverage[toml]~=7.5.0; extra == "dev"
Requires-Dist: flake8==4.0.1; extra == "dev"
Requires-Dist: ipykernel==6.9.1; extra == "dev"
Requires-Dist: matplotlib>=3.5.2; extra == "dev"
Requires-Dist: numpy!=2.0.*; extra == "dev"
Requires-Dist: pre-commit; extra == "dev"
Requires-Dist: pytest==7.1.2; extra == "dev"
Requires-Dist: scikit-image==0.19.2; extra == "dev"
Requires-Dist: sphinx==7.2.6; extra == "dev"
Requires-Dist: sphinx-press-theme==0.8.0; extra == "dev"
Requires-Dist: twine==4.0.0; extra == "dev"
Dynamic: license-file
